pulumi_castai/__init__.py
pulumi_castai/_inputs.py
pulumi_castai/_utilities.py
pulumi_castai/aks_cluster.py
pulumi_castai/autoscaler.py
pulumi_castai/cluster.py
pulumi_castai/cluster_token.py
pulumi_castai/credentials.py
pulumi_castai/eks_cluster.py
pulumi_castai/get_cluster_data_source.py
pulumi_castai/get_credentials_data_source.py
pulumi_castai/get_eks_cluster_id_data_source.py
pulumi_castai/get_eks_settings_data_source.py
pulumi_castai/get_eks_user_arn_data_source.py
pulumi_castai/get_gke_policies_data_source.py
pulumi_castai/gke_cluster.py
pulumi_castai/outputs.py
pulumi_castai/provider.py
pulumi_castai/pulumi-plugin.json
pulumi_castai/py.typed
pulumi_castai/config/__init__.py
pulumi_castai/config/__init__.pyi
pulumi_castai/config/vars.py
pulumi_castai-0.1.87.dist-info/METADATA
pulumi_castai-0.1.87.dist-info/WHEEL
pulumi_castai-0.1.87.dist-info/top_level.txt
pulumi_castai-0.1.87.dist-info/RECORD
